<PAMDataset>
  <PAMRasterBand band="1">
    <Histograms>
      <HistItem>
        <HistMin>4.997500010490418</HistMin>
        <HistMax>10.00247900867462</HistMax>
        <BucketCount>1000</BucketCount>
        <IncludeOutOfRange>0</IncludeOutOfRange>
        <Approximate>0</Approximate>
        <HistCounts>73|137|131|129|130|125|136|131|127|142|125|131|121|124|121|124|116|115|129|113|129|117|118|125|108|139|107|128|126|113|119|131|124|122|122|124|127|124|118|123|124|112|121|117|111|127|110|118|124|111|112|127|119|120|113|117|120|126|106|124|124|111|131|117|116|118|127|114|133|118|117|137|116|125|125|119|131|127|127|127|128|126|137|121|140|129|118|145|125|138|128|128|165|121|134|153|131|133|152|137|134|155|143|152|142|151|147|149|155|157|141|162|144|168|157|165|148|169|165|171|157|167|170|182|167|174|176|183|173|189|169|203|183|182|197|202|192|204|200|193|210|215|194|217|229|205|223|234|228|237|231|232|242|243|226|254|221|262|234|248|251|251|233|272|249|262|262|263|263|263|294|264|287|283|288|292|313|305|319|287|360|332|330|379|370|382|429|419|547|533|490|418|415|403|402|391|386|411|421|509|554|385|387|345|368|326|323|322|318|300|301|296|283|280|277|289|266|269|260|257|255|261|248|248|239|241|237|234|239|235|226|218|233|215|224|220|220|206|223|212|214|202|205|205|212|192|200|217|181|200|207|174|202|203|186|191|192|191|186|188|186|180|198|173|195|181|181|190|167|184|178|193|159|187|187|173|165|192|161|182|170|189|166|157|197|171|159|181|177|169|147|217|151|167|171|180|161|164|190|159|159|179|182|155|186|164|167|173|174|154|179|175|174|153|181|171|172|168|165|186|158|168|192|159|166|183|165|172|182|169|170|180|173|163|187|188|170|164|183|183|173|171|185|193|175|171|209|169|179|175|206|173|193|188|195|191|190|185|202|195|190|203|201|199|198|198|228|195|212|204|226|207|217|232|219|221|243|214|240|252|238|248|249|277|255|264|295|279|291|314|335|336|361|383|435|462|534|651|923|2462|2488|1380|1215|1051|988|895|899|836|810|793|775|740|739|719|703|708|697|675|690|673|665|670|665|652|679|648|668|681|653|679|673|690|708|717|788|957|964|943|942|914|894|888|855|867|818|825|830|793|783|770|774|757|732|737|742|696|707|713|695|681|672|653|683|648|633|651|642|626|611|624|613|589|629|584|592|587|581|590|546|585|578|544|559|560|547|550|524|552|559|522|516|542|520|527|520|525|504|510|505|525|516|492|501|510|498|486|487|518|481|491|490|517|493|468|490|502|484|456|498|502|467|488|494|492|480|504|488|493|499|482|515|501|499|508|551|528|535|639|567|559|519|504|512|476|517|479|476|478|479|480|476|477|483|475|476|488|454|462|445|466|440|435|441|425|417|446|416|397|424|402|402|395|377|417|391|373|383|366|373|376|362|370|359|346|368|351|340|342|343|345|348|314|338|315|338|305|345|296|333|283|270|241|257|233|243|241|251|241|218|251|219|233|223|235|220|224|209|237|217|214|208|218|209|208|215|198|204|203|206|191|201|201|188|199|187|201|194|182|175|183|198|170|197|176|167|184|177|184|167|179|166|165|171|164|183|159|164|153|160|176|148|168|157|137|171|147|158|165|134|158|154|137|162|141|147|150|130|148|146|134|153|123|141|154|116|138|138|139|134|133|126|128|134|123|151|108|122|135|118|126|130|126|119|113|122|122|116|119|129|108|111|120|113|123|108|120|109|109|116|114|98|114|105|107|108|119|94|105|105|107|101|113|89|103|110|86|106|109|96|93|99|98|89|107|98|97|87|105|76|100|97|101|88|86|92|82|90|101|99|74|87|81|93|80|100|93|72|84|84|89|76|95|83|79|73|89|78|78|89|77|81|78|86|60|92|75|73|80|71|85|62|91|72|73|78|71|74|70|83|66|64|88|61|70|70|76|68|67|78|72|61|64|77|73|54|73|65|66|67|69|68|61|60|66|72|69|52|63|71|55|63|68|70|50|57|70|65|57|56|70|59|50|63|71|53|57|57|63|59|51|62|54|64|52|57|54|57|57|53|61|58|44|59|54|61|52|53|54|49|49|66|52|49|51|53|48|56|56|53|40|54|49|51|55|53|45|53|45|50|45|58|47|49|36|54|51|48|50|43|45|51|47|55|35|51|43|46|42|52|50|38|41|46|48|49|45|38|43|44|57|39|34|45|42|51|43|33|46|45|36|52|43|32|39|47|47|34|42|40|42|45|36|41|37|41|45|41|24|53|44|33|38|34|42|38|41|34|42|37|40|33|46|35|30|44|37|34|38|35|41|35|31|36|42|30|45|30|34|39|32|41|32|38|29|40|30|33|37|35|32|37|32|36|34|31|35|35|32|32|18</HistCounts>
      </HistItem>
    </Histograms>
    <Metadata>
      <MDI key="STATISTICS_MAXIMUM">9.999979019165</MDI>
      <MDI key="STATISTICS_MEAN">7.1538661059989</MDI>
      <MDI key="STATISTICS_MINIMUM">5</MDI>
      <MDI key="STATISTICS_STDDEV">0.98107880198886</MDI>
    </Metadata>
  </PAMRasterBand>
</PAMDataset>
